MANIFEST.in
README.md
readme.md
setup.py
bin/ictrainer
ictrainer/__init__.py
ictrainer/color.py
ictrainer/const.py
ictrainer/face_detector.py
ictrainer/ictrainer.py
ictrainer/image_collector.py
ictrainer/image_resizer.py
ictrainer/image_size_check.py
ictrainer/test.py
ictrainer.egg-info/PKG-INFO
ictrainer.egg-info/SOURCES.txt
ictrainer.egg-info/dependency_links.txt
ictrainer.egg-info/requires.txt
ictrainer.egg-info/top_level.txt