Metadata-Version: 2.1
Name: ictrainer
Version: 0.2.5
Summary: cli tool for training your own image classifier with one line command!
Home-page: https://github.com/koji/ictrainer
Author: koji kanao
Author-email: koji.kanao@nyu.edu
License: MIT
Platform: UNKNOWN
